pytcp/__init__.py
pytcp/config.py
pytcp/lib/ip4_address.py
pytcp/lib/ip6_address.py
pytcp/lib/ip_address.py
pytcp/lib/ip_helper.py
pytcp/lib/logger.py
pytcp/lib/mac_address.py
pytcp/lib/packet.py
pytcp/lib/packet_stats.py
pytcp/lib/socket.py
pytcp/lib/stack.py
pytcp/lib/tracker.py
pytcp/lib/tx_status.py
pytcp/protocols/arp/fpa.py
pytcp/protocols/arp/fpp.py
pytcp/protocols/arp/phrx.py
pytcp/protocols/arp/phtx.py
pytcp/protocols/arp/ps.py
pytcp/protocols/dhcp4/client.py
pytcp/protocols/dhcp4/ps.py
pytcp/protocols/ether/fpa.py
pytcp/protocols/ether/fpp.py
pytcp/protocols/ether/phrx.py
pytcp/protocols/ether/phtx.py
pytcp/protocols/ether/ps.py
pytcp/protocols/icmp4/fpa.py
pytcp/protocols/icmp4/fpp.py
pytcp/protocols/icmp4/phrx.py
pytcp/protocols/icmp4/phtx.py
pytcp/protocols/icmp4/ps.py
pytcp/protocols/icmp6/fpa.py
pytcp/protocols/icmp6/fpp.py
pytcp/protocols/icmp6/phrx.py
pytcp/protocols/icmp6/phtx.py
pytcp/protocols/icmp6/ps.py
pytcp/protocols/ip4/fpa.py
pytcp/protocols/ip4/fpp.py
pytcp/protocols/ip4/phrx.py
pytcp/protocols/ip4/phtx.py
pytcp/protocols/ip4/ps.py
pytcp/protocols/ip6/fpa.py
pytcp/protocols/ip6/fpp.py
pytcp/protocols/ip6/phrx.py
pytcp/protocols/ip6/phtx.py
pytcp/protocols/ip6/ps.py
pytcp/protocols/ip6_ext_frag/fpa.py
pytcp/protocols/ip6_ext_frag/fpp.py
pytcp/protocols/ip6_ext_frag/phrx.py
pytcp/protocols/ip6_ext_frag/phtx.py
pytcp/protocols/ip6_ext_frag/ps.py
pytcp/protocols/raw/fpa.py
pytcp/protocols/tcp/fpa.py
pytcp/protocols/tcp/fpp.py
pytcp/protocols/tcp/metadata.py
pytcp/protocols/tcp/phrx.py
pytcp/protocols/tcp/phtx.py
pytcp/protocols/tcp/ps.py
pytcp/protocols/tcp/session.py
pytcp/protocols/tcp/socket.py
pytcp/protocols/udp/fpa.py
pytcp/protocols/udp/fpp.py
pytcp/protocols/udp/metadata.py
pytcp/protocols/udp/phrx.py
pytcp/protocols/udp/phtx.py
pytcp/protocols/udp/ps.py
pytcp/protocols/udp/socket.py
pytcp/subsystems/arp_cache.py
pytcp/subsystems/nd_cache.py
pytcp/subsystems/packet_handler.py
pytcp/subsystems/rx_ring.py
pytcp/subsystems/timer.py
tcp_ip_stack-2.7.0.dist-info/LICENSE
tcp_ip_stack-2.7.0.dist-info/METADATA
tcp_ip_stack-2.7.0.dist-info/WHEEL
tcp_ip_stack-2.7.0.dist-info/top_level.txt
tcp_ip_stack-2.7.0.dist-info/RECORD
