Metadata-Version: 2.1
Name: tcp-ip-stack
Version: 2.7.0
Summary: TCP/IP stack written in Python.
Author-email: Sebastian Majewski <ccie18643@gmail.com>
License: GNU GENERAL PUBLIC LICENSE
Project-URL: Homepage, https://github.com/ccie18643/PyTCP
Project-URL: Bug Tracker, https://github.com/ccie18643/PyTCP/issues
Keywords: networking,tcpip,stack
Classifier: Programming Language :: Python :: 3.10
Classifier: License :: OSI Approved :: GNU General Public License v3 (GPLv3)
Classifier: Development Status :: 3 - Alpha
Classifier: Operating System :: POSIX :: Linux
Classifier: Natural Language :: English
Classifier: Environment :: Console
Classifier: Topic :: System :: Networking
Classifier: Typing :: Typed
Requires-Python: >=3.10
License-File: LICENSE
Provides-Extra: dev
Requires-Dist: click ; extra == 'dev'
Requires-Dist: testslide ; extra == 'dev'
Requires-Dist: black ; extra == 'dev'
Requires-Dist: mypy ; extra == 'dev'
Requires-Dist: flake8 ; extra == 'dev'
Requires-Dist: codespell ; extra == 'dev'
Requires-Dist: isort ; extra == 'dev'
Requires-Dist: pylint ; extra == 'dev'
Requires-Dist: build ; extra == 'dev'
Requires-Dist: twine ; extra == 'dev'
